Metadata-Version: 2.1
Name: tea-cli
Version: 1.3.2
Summary: tea, a complete version control system.
Home-page: https://github.com/lizardwine/tea
Author: Lizardwine
Author-email: lizardwine@hotmail.com
License: GPL v3.0
Keywords: version,control,versioning,file
Classifier: License :: OSI Approved :: GNU General Public License v3 (GPLv3)
Classifier: Development Status :: 5 - Production/Stable
Classifier: Intended Audience :: Developers
Classifier: Natural Language :: English
Classifier: Operating System :: Unix
Classifier: Programming Language :: Python :: 3
Classifier: Topic :: Software Development
Classifier: Topic :: Software Development :: Version Control
Requires-Python: >=3.7
License-File: LICENSE
